MANIFEST.in
README.md
README.rst
requirements.txt
setup.py
src/paas_star/__init__.py
src/paas_star/logger.py
src/paas_star.egg-info/PKG-INFO
src/paas_star.egg-info/SOURCES.txt
src/paas_star.egg-info/dependency_links.txt
src/paas_star.egg-info/entry_points.txt
src/paas_star.egg-info/requires.txt
src/paas_star.egg-info/top_level.txt
src/paas_star/backend/__init__.py
src/paas_star/backend/clients/__init__.py
src/paas_star/backend/clients/iam.py
src/paas_star/backend/iam/__init__.py
src/paas_star/backend/iam/iam.py
src/paas_star/backend/kafka/__init__.py
src/paas_star/backend/kafka/kafka_consumer.py
src/paas_star/backend/kafka/kafka_producer.py
src/paas_star/backend/mongo/__init__.py
src/paas_star/backend/mongo/mongo.py
src/paas_star/backend/mongodb/__init__.py
src/paas_star/backend/mongodb/mongodb.py
src/paas_star/backend/routing/__init__.py
src/paas_star/backend/routing/routing.py
src/paas_star/backend/s3/__init__.py
src/paas_star/backend/s3/dummy_s3.py
src/paas_star/backend/s3/s3.py
src/paas_star/build/__init__.py
src/paas_star/build/tasks.py
src/paas_star/components/__init__.py
src/paas_star/components/model.py
src/paas_star/components/repository.py
src/paas_star/components/session.py
src/paas_star/templates/backend/__init__.py
src/paas_star/templates/backend/${module_name}/${module_name}.py.tmpl
src/paas_star/templates/backend/${module_name}/__init__.py.tmpl
src/paas_star/templates/project/.gitlab-ci.yml.tmpl
src/paas_star/templates/project/Dockerfile.tmpl
src/paas_star/templates/project/MANIFEST.in.tmpl
src/paas_star/templates/project/README.md.tmpl
src/paas_star/templates/project/README.rst.tmpl
src/paas_star/templates/project/deploy.json.tmpl
src/paas_star/templates/project/requirements.txt.tmpl
src/paas_star/templates/project/setup.py.tmpl
src/paas_star/templates/project/src/${name}/__init__.py
src/paas_star/templates/project/src/${name}/settings.py.tmpl
src/paas_star/templates/project/src/${name}/start_webapp.sh.tmpl
src/paas_star/templates/project/src/${name}/web_app.py.tmpl
src/paas_star/templates/project/src/${name}/${name}/__init__.py
src/paas_star/templates/service/__init__.py.tmpl
src/paas_star/templates/service/repository.py.tmpl
