Metadata-Version: 1.0
Name: paas-star
Version: 0.2.2
Summary: package description here
Home-page: UNKNOWN
Author: shichao.ma
Author-email: shichao.ma@yiducloud.cn
License: UNKNOWN
Platform: UNKNOWN
